examples/__init__.py
examples/vt_to_geodataframe.py
tests/__init__.py
tests/test_conversions.py
vt2geojson/__init__.py
vt2geojson/cli.py
vt2geojson/features.py
vt2geojson/tools.py
vt2geojson-0.2.1.dist-info/LICENSE
vt2geojson-0.2.1.dist-info/METADATA
vt2geojson-0.2.1.dist-info/WHEEL
vt2geojson-0.2.1.dist-info/entry_points.txt
vt2geojson-0.2.1.dist-info/top_level.txt
vt2geojson-0.2.1.dist-info/RECORD
