Metadata-Version: 2.1
Name: vt2geojson
Version: 0.2.1
Summary: Dump vector tiles to GeoJSON from remote URLs or local system files.
Home-page: https://github.com/Amyantis/python-vt2geojson
Author: Theophile Dancoisne
Author-email: dancoisne.theophile@gmail.com
License: UNKNOWN
Platform: UNKNOWN
License-File: LICENSE
